README.rst
setup.py
Yasuf.egg-info/PKG-INFO
Yasuf.egg-info/SOURCES.txt
Yasuf.egg-info/dependency_links.txt
Yasuf.egg-info/requires.txt
Yasuf.egg-info/top_level.txt
yasuf/__init__.py
yasuf/test.py
yasuf/utils.py
yasuf/yasuf.py