Metadata-Version: 1.0
Name: Yasuf
Version: 0.5.dev0
Summary: Simple framwork for executing python functions via Slack
Home-page: https://github.com/sYnfo/Yasuf
Author: Matej Stuchlik
Author-email: matej.stuchlik@gmail.com
License: UNKNOWN
Platform: UNKNOWN
